{"title":"Expressen","url":"https://www.expressen.se","favicon":"https://static.cdn-expressen.se/bundles/expressen/images/favicon.ico","elements":[{"title":"JUST NU: Spritstopp på Mallorca","contents":"Slaget mot turisterna • Ving: ”Utmärkt”","link":"https://www.expressen.se/nyheter/sverige/slaget-mot-turisterna-spritstopp-pa-mallorca/","retrieved":1715357401606},{"title":"Ukrainska krisdraget efter ryska offensiven","contents":"”Kritisk fas\" • Då kan läget vändas mot Ryssland","link":"https://www.expressen.se/nyheter/varlden/ukrainska-krisdraget-efter-ryska-offensiven/","retrieved":1715357401607},{"title":"Ukrainskt drönaranfall satte nytt distansrekord","contents":"Fick in fullträff efter 150 mil","link":"https://www.expressen.se/nyheter/varlden/kriget-i-ukraina-10-maj/","retrieved":1715357401608},{"title":"Ny attack i Ryssland – raffinaderi i lågor","contents":"Bilder visar kraftiga branden","link":"https://www.expressen.se/tv/nyheter/varlden/ny-attack-inne-i-ryssland-raffinaderi-star-i-lagor/","retrieved":1715357401608},{"title":"Ovanliga fyndet på verkstaden","contents":"\"Sötaste någonsin\"","link":"https://www.expressen.se/tv/nyheter/sverige/sotchocken-i-bilverkstaden-i-skene/","retrieved":1715357401609},{"title":"Mördarens iskalla ord om mördade surfarna","contents":"Skröt för flickvännen: ”Dödat tre gringos”","link":"https://www.expressen.se/nyheter/varlden/mordaren-skrot-for-sin-flickvan-dodat-tre-gringos/","retrieved":1715321426153},{"title":"De tror inte sina ögon – slukhålet sväljer bil","contents":"Udda kedjereaktion i Phoenix","link":"https://www.expressen.se/tv/nyheter/varlden/de-tror-inte-sina-ogon-slukhalet-svaljer-bil/","retrieved":1715339271043},{"title":"Israels oro i Eurovision: Rädda jurymedlemmar","contents":"Israeliska fans: Politiken avgör • Tror på folkets röst","link":"https://www.expressen.se/nyheter/varlden/eurovision-2024-israel-tror-pa--folkets-stod-men-fruktar-juryn/","retrieved":1715357401611},{"title":"Poliskritik: ”Känner mig inte tryggare”","contents":"Prickskyttar och massiv bevakning","link":"https://www.expressen.se/nyheter/sverige/kritik-mot-prickskyttar-och-polisbevakning-i-malmo/","retrieved":1715357401612},{"contents":"<video style=\"width:100%;min-width:10px;aspect-ratio:16/9;display:block;\" src=\"https://0376f126355e5c53482bd45bc6430395-httpcache0-03837-cachedown0.dna.ip-only.net/03837-cachedown0/ncode/2024-05-10/tvtool06dcacce-a4ff-424f-9309-636d323ad3be_1715348963196/tvtool06dcacce-a4ff-424f-9309-636d323ad3be_1715348963196_576p.mp4\" autoplay=\"\" loop=\"\" muted=\"\" playsinline=\"\"></video>","link":"https://www.expressen.se/tv/nyheter/varlden/buss-stortar-ner-i-ryska-floden-","retrieved":1715357401453},{"title":"Här störtar bussen ner i ryska floden","contents":"Många passagerare ombord","link":"https://www.expressen.se/tv/nyheter/varlden/buss-stortar-ner-i-ryska-floden-/","retrieved":1715357401612},{"title":"Bror dödade sin syster under bråk","contents":"Dog av sina skador – yngre man gripen i Göteborg","link":"https://www.expressen.se/nyheter/sverige/bror-misstanks-ha-dodat-sin-syster-i-goteborg/","retrieved":1715332187353},{"contents":"<span class=\"bb--red\">TIPSA: </span>Vet du mer? Sms:a 0790-643643","link":"https://www.expressen.se/nyheter/har-du-ett-nyhetstips-eller-bilder/","retrieved":1715184627541},{"title":"Därför släpper HBO sina serier på Netflix","contents":"PODD: Så påverkas tittarna","link":"https://www.expressen.se/nyheter/laget/darfor-slapper-hbo-sina-serier-pa-netflix/","retrieved":1715357401614},{"contents":"Tips på bröllopspresenter – det här vill brudparet ha","link":"https://www.expressen.se/skonahem/nyheter/shopping/brollopspresenter-2024-tips-personligt-till-brudparet/","retrieved":1714716647861},{"title":"Kvinna hittades död – tre begärs häktade","contents":"Kroppen låg bränd i ett vindskydd i Lessebo","link":"https://www.expressen.se/nyheter/sverige/kvinna-hittades-dod-i-vindskydd-tre-gripna-i-lessebo/","retrieved":1715332187368},{"contents":"<span class=\"bb--red\">TIPSA: </span>Vet du mer? Sms:a 0790-643643","link":"https://www.expressen.se/nyheter/har-du-ett-nyhetstips-eller-bilder/","retrieved":1715184627541},{"title":"Testa valkompassen: Vem ska du rösta på?","contents":"9 juni är det EU-val – vilket parti företräder dina åsikter?","link":"https://www.expressen.se/nyheter/varlden/valkompass-eu-val-2024-testa-sjalv-vilket-parti-ska-du-rosta-pa-den-9-juni/","retrieved":1711469387039},{"title":"Svensk jagas – ska ha lett pedofilring","contents":"Influencer lockade med sex – barn våldtogs •&nbsp;Värsta härvan någonsin i Libanon","link":"https://www.expressen.se/nyheter/varlden/svensk-jagas-ska-ha-lett-pedofilring/","retrieved":1715321426121},{"title":"L-topp: M äventyrar EU:s stöd till Ukraina","contents":"Liberalernas angrepp: De måste ge svar om ytterhögern","link":"https://www.expressen.se/nyheter/varlden/l-topp-m-maste-ge-svar-om-ytterhogern/","retrieved":1715321426123},{"title":"14 nyckelbärare vaktar internet – en är Pia, 62","contents":"”Ingen ska kunna hitta på något fuffens” • Så går det till","link":"https://www.expressen.se/nyheter/sverige/14-nyckelbarare-vaktar-internet-en-ar-pia-62/","retrieved":1715321426122},{"title":"Tv-bilderna från Putins stora parad förbryllar","contents":"Ovanligt glest på Röda torget","link":"https://www.expressen.se/tv/nyheter/varlden/segerparaden-i-moskva-blev-inte-som-den-brukar/","retrieved":1715357401623},{"title":"Enorma slukhålet till havs har ingen botten","contents":"Djupet förbryllar forskarna • Kampen i ”skymningszonen” vid Mexikos kust","link":"https://www.expressen.se/tv/nyheter/varlden/enorma-slukhalet-till-havs-har-ingen-botten","retrieved":1715339271043},{"title":"Oscar Engelbert lämnar krisande fastighetsbolag","contents":"Oscar Properties ansöker om rekonstruktion","link":"https://www.expressen.se/nyheter/sverige/oscar-engelbert-lamnar-krisande-fastighetsbolaget/","retrieved":1715357401625},{"title":"Chocken i trädgården: ”Det sötaste jag sett”","contents":"Knepet för att rädda sälen i Skelleftehamn – en kilometer från kusten","link":"https://www.expressen.se/tv/nyheter/sverige/chocken-i-tradgarden-det-sotaste-jag-sett","retrieved":1715332187354},{"title":"Nicole hamnade mitt i bråket på flygplanet","contents":"Flygvärdinnans drag: Mänsklig sköld • Kaos på flygplatsen i Boston","link":"https://www.expressen.se/tv/nyheter/varlden/flygplansbrak-urartar-kaoset-efter-landning-","retrieved":1715339271053},{"title":"USA:s försäkran efter hotet: Delar Israels mål","contents":"”Dundra in i Rafah främjar inte målet”","link":"https://www.expressen.se/nyheter/varlden/usas-forsakran-till-israel-efter-bidens-hot/","retrieved":1715321426140},{"title":"Struntar i Biden: ”Står ensamma om vi måste”","contents":"Israels premiärminister går emot USA:s vapenhot","link":"https://www.expressen.se/nyheter/varlden/netanyahu-vi-star-ensamma-om-vi-maste/","retrieved":1715321426142},{"title":"Desperata scenerna i Rafah – blodiga barn","contents":"Varning för starka bilder • Flera barn dödade i israelisk attack","link":"https://www.expressen.se/tv/nyheter/varlden/desperata-scenerna-i-rafah-blodiga-barn-pa-sjukhuset","retrieved":1715270962434},{"title":"Strömmers oro för svenska fängelser","contents":"Efter Expressens rapportering: ”Systemhotande”","link":"https://www.expressen.se/nyheter/sverige/strommer-om-fangarnas-relationer-med-vakterna/","retrieved":1715270962413},{"title":"Fångarna flyttade in hos kriminalvårdare","contents":"”Storkär” • Förnekar, trots bevis • Får jobba kvar","link":"https://www.expressen.se/nyheter/sverige/kriminalvardarna-flyttade-ihop-med-ex-fangar-storkar/","retrieved":1715148613865},{"title":"Fritagningshot och infiltration på häktena","contents":"Hör ”Krimrummet”&nbsp;om krisen i Kriminalvården","link":"https://www.expressen.se/nyheter/sverige/fritagningshot-och-infiltration-pa-haktena/","retrieved":1715270962413},{"title":"”Putins attackhund” hyllas – av Röda korset-chefen","contents":"Lovordade Tjetjeniens president: ”Lugn och karismatisk”","link":"https://www.expressen.se/nyheter/varlden/roda-korset-chefens-hyllning-av-diktatorn-ramzan-kadyrov/","retrieved":1715321426151},{"title":"Barn dog efter fall på skola – rektor åtalas","contents":"Föll från berg i Göteborg • ”Tuff tid för mamman”","link":"https://www.expressen.se/nyheter/sverige/rektor-atalas-efter-barn-fallit-och-dott/","retrieved":1715357401641},{"title":"Massutbrott på solen – geomagnetisk storm hotar","contents":"Fem utkastningar på väg mot jorden – påverkar hela helgen","link":"https://www.expressen.se/nyheter/varlden/massutbrott-pa-solen-geomagnetiska-stormar-pa-vag/","retrieved":1715321426132},{"title":"”Du har haft sex i över 200 porrfilmer, eller hur?”","contents":"Stormy Daniels grillad av Donald Trumps advokat","link":"https://www.expressen.se/nyheter/varlden/stormy-daniels-grillad-av-donald-trumps-advokat/","retrieved":1715321426129},{"title":"”När har han någonsin gjort det han har sagt?”","contents":"Joe Biden går hårt åt Donald Trump i CNN-intervju","link":"https://www.expressen.se/tv/nyheter/varlden/biden-nar-har-trump-nagonsin-gjort-det-han-sagt","retrieved":1715245739325},{"title":"Oljeattack djupt inne i Ryssland: ”Rekord”","contents":"Slog till mot raffinaderi","link":"https://www.expressen.se/tv/nyheter/varlden/attack-djupt-inne-i-ryssland-stortar-flygplan-i-oljeraffinaderi-/","retrieved":1715321426156},{"title":"Macron backar – efter ryska hotet","contents":"”Ingen önskan om regimskifte”","link":"https://www.expressen.se/nyheter/varlden/macron-backar-efter-ryska-hotet/","retrieved":1715321426157},{"title":"Bilkaravan med ryska flaggor i Stockholm","contents":"Hyllar Ryssland och Sovjet","link":"https://www.expressen.se/nyheter/sverige/bilkaravan-i-stockholm-viftar-med-ryska-flaggor/","retrieved":1715270962404},{"title":"Putins mardröm: Kan bli ”industrimuseum”","contents":"Experterna om Rysslands ekonomi – efter kriget","link":"https://www.expressen.se/nyheter/varlden/putins-mardrom-landet--kan-bli-industrimuseum/","retrieved":1715245739284},{"title":"Trumps yngste son gör politisk debut","contents":"Barron Trump, 18, utses till delegat i Florida","link":"https://www.expressen.se/nyheter/varlden/politisk-debut-for-yngste-sonen-trump/","retrieved":1715332187379},{"title":"Kvinna bodde inne i butikens takskyltning","contents":"”Tak-ninjan” bodde på butikens tak i ett år","link":"https://www.expressen.se/nyheter/varlden/kvinna-bodde-inne-i-butikens-takskyltning/","retrieved":1715321426154},{"title":"Fintar helikopter – går rakt mot krigsskeppet","contents":"Ukrainsk sjödrönare går till attack","link":"https://www.expressen.se/tv/nyheter/varlden/kampen-pa-svarta-havet-ukrainska-batdronare-mot-rysk-militar/","retrieved":1715270962402},{"title":"Anderssons utspel på V-kongressen: ”Mjau”","contents":"Kängan till regeringen","link":"https://www.expressen.se/tv/nyheter/sverige/andersson-utspel-pa-v-kongressen-mjau","retrieved":1715270962399},{"title":"Utspelet mot rivalerna: ”Äta fem hjärnmaskar”","contents":"”RFK” till Trump och Biden efter att ha drabbats av hjärnätande parasit","link":"https://www.expressen.se/nyheter/varlden/rfks-utspel-efter-nyhet-om-hjarnatande-parasit-/","retrieved":1715321426163},{"title":"Julia Rausings tragedier: Mord, otrohet och svek","contents":"Förlorade två syskon • Kärleksdrama • Fråntogs arv","link":"https://www.expressen.se/nyheter/tragedierna-i-julia-rausings-liv-mord-och-otrohet-/","retrieved":1715270962394},{"title":"Blev arg på sin mamma – sköt henne i sängen","contents":"Orden i förhör: ”Gått snett i huvudet”","link":"https://www.expressen.se/nyheter/sverige/blev-arg-pa-sin-mamma-skot-henne-med-algstudsare/","retrieved":1715235068986},{"title":"Efter regn och rusk – värme i hela landet","contents":"”Sommarvärme” –&nbsp;även i norra Norrland","link":"https://www.expressen.se/nyheter/sverige/efter-regn-och-rusk-varme-i-hala-landet/","retrieved":1715270962435},{"title":"Kinas nya skrytbygge – en utmanare till USA","contents":"Se enorma hangarfartyget Fujians jungfrufärd","link":"https://www.expressen.se/tv/nyheter/varlden/kinas-nya-skrytbygge-ska-utmana-usa/","retrieved":1715270962399}]}