{"title":"Svenska Dagbladet","url":"https://www.svd.se","favicon":"https://static.svd.se/assets/assets/images/favicon/favicon-32x32.png","elements":[{"title":"Alltid senaste nytt – följ SvD direkt","contents":"<span class=\"LabelLive-www__sc-1prgiuu-0 cDNrGJ\"><span class=\"LiveDot-www__sc-1prgiuu-1 gtvDUq\"></span>Direkt</span>Liverapport med de senaste nyheterna.","link":"https://www.svd.se/a/wA9Gmd/senaste-nytt","retrieved":1714295243193},{"title":"”En stor skillnad på Liberalerna och Macron”","contents":"L-toppen är positivt överraskad av Tidöavtalet – himlar med ögonen åt C-strategin.","link":"https://www.svd.se/a/yERX9a/liberalernas-karin-karlsbro-vill-inte-samarbeta-med-sd","retrieved":1716999022740,"image":"https://svd.vgc.no/v2/images/30c0a674-0c2e-42be-b694-162ac4681b15?fit=crop&format=jpeg&h=375&q=80&upscale=true&w=666&s=1b39c23142e062331f493f7ec49639e1a3ab5767"},{"title":"Vilket parti ligger dig närmast i EU-valet?","contents":"SvD:s valkompass hjälper dig hitta rätt inför valet 9 juni.","link":"https://www.svd.se/a/zEdvlv/valkompass-eu-valet-2024-vilket-parti-ligger-dig-narmast","retrieved":1716999022740,"image":"https://svd.vgc.no/v2/images/000fe9cd-95bc-4a79-b115-8c763197c186?fit=crop&format=jpeg&h=90&q=80&tight=true&upscale=true&w=160&s=93f4508e8ccac21ffc3599041985a0f8a9279a55"},{"title":"Två kvinnor häktade misstänkta för grov våldtäkt","contents":"Sju personer greps, men fem män har nu släpptes.","link":"https://www.svd.se/a/eMKBGO/tva-kvinnor-haktade-for-grov-valdtakt-i-rissne","retrieved":1716999022740},{"title":"SD-medarbetare slutar efter Putinhyllningar","contents":"Figurerade i Kalla Faktas granskning • Statsministern kallar avslöjandet för helt förfärligt.","link":"https://www.svd.se/a/0VKzm2/kristersson-om-sd-medarbetaren-helt-forfarligt","retrieved":1716999022742},{"title":"Nytt vulkanutbrott på Island – stad evakueras","contents":"Geofysikern: ”Öppnade sig med kraft” • Tre personer uppges vägra lämna Grindavik.","link":"https://www.svd.se/a/B0l2qQ/grindavik-evakueras-risk-for-nytt-vulkanutbrott","retrieved":1716999022743},{"title":"\"All eyes on Rafah\" sprids av miljontals","contents":"Experten: ”En symbolisk bild som fler kan ställa sig bakom.”","link":"https://www.svd.se/a/0VKJ2E/all-eyes-on-rafah-bilden-sprids-av-miljontals","retrieved":1716999022746},{"title":"Bidens dilemma: när är gränsen nådd i Gaza?","contents":"Trycket på Vita huset ökar efter helgens bombattack mot flyktingläger.","link":"https://www.svd.se/a/JbJwL7/bidens-dilemma-var-gar-usa-s-grans-for-rod-linje-i-gaza","retrieved":1716999022748},{"title":"Israeliska stridsvagnar uppges avancera i Rafah","contents":"<span class=\"LabelLive-www__sc-1prgiuu-0 cDNrGJ\"><span class=\"LiveDot-www__sc-1prgiuu-1 gtvDUq\"></span>Direkt</span>AFP:s reporter beskriver pågående gatustrider och beskjutning från helikoptrar • Senaste nytt.","link":"https://www.svd.se/a/dwel81/senaste-nytt-om-israel-palestina-konflikten","retrieved":1715684871565},{"title":"”Skarpaste tänkaren” har fått tänka om","contents":"<strong>Lisa Irenius: </strong>Det Europa som spåddes styra århundradet beskrivs nu som hotat.","link":"https://www.svd.se/a/OoQ1mk/lisa-irenius-skarpa-eu-tankaren-har-fatt-tanka-om","retrieved":1716999022761},{"title":"”Vi har verkligen lyssnat på Ukrainas behov”","contents":"Nya stödpaketet är det största hittills – innebär tillfällig nedsättning av svensk försvarsförmåga.","link":"https://www.svd.se/a/VzqrB6/regeringen-presenterar-nytt-vapenstod-till-ukraina-vart-13-miljarder","retrieved":1716980882983},{"title":"Paasikivi: Paketet är ”nödvändigt och viktigt”","contents":"Ska hjälpa vid fronten och stärka landets förmåga att freda sig.","link":"https://www.svd.se/a/alP0BO/paasikivi-paketet-till-ukraina-nodvandigt-och-viktigt","retrieved":1716973784614},{"title":"Putin varnar väst för att leverera vapen","contents":"<span class=\"LabelLive-www__sc-1prgiuu-0 cDNrGJ\"><span class=\"LiveDot-www__sc-1prgiuu-1 gtvDUq\"></span>Direkt</span>”Bör vara medveten om vad man leker med” • Senaste nytt.","link":"https://www.svd.se/a/ja1n9q/konflikten-mellan-ukraina-och-ryssland-har-ar-senaste-nytt","retrieved":1715850494730},{"title":"Vårdslöst av SVT att sända konflikten","contents":"<strong>Andreas Hörmark: </strong>Paret hoppar av – nu undrar tittarna vad som hänt.","link":"https://www.svd.se/a/OoQagE/gift-vid-forsta-ogonkastet-avsnittet-i-svt-vacker-obehaglig-fraga","retrieved":1716973784631},{"title":"Björn Lund: Utbrottet kan bli långvarigt","contents":"<div class=\"BodyContent-www__sc-uz9q9i-1 hoMPxp\"><h2 class=\"Heading-www__sc-uz9q9i-2 bIqExJ Teaser-heading\">Björn Lund: Utbrottet kan bli långvarigt</h2></div>","link":"https://www.svd.se/a/B0lBk0/bjorn-lund-utbrottet-kan-bli-langvarigt","retrieved":1716999022718},{"title":"Regeringen: Fler ska avtjäna straff utomlands","contents":"<div class=\"BodyContent-www__sc-uz9q9i-1 hoMPxp\"><h2 class=\"Heading-www__sc-uz9q9i-2 bIqExJ Teaser-heading\">Regeringen: Fler ska avtjäna straff utomlands</h2></div>","link":"https://www.svd.se/a/8q6o5w/regeringen-fler-ska-avtjana-straff-utomlands","retrieved":1716999022718},{"title":"Trumps öde i juryns händer","contents":"<div class=\"BodyContent-www__sc-uz9q9i-1 hoMPxp\"><h2 class=\"Heading-www__sc-uz9q9i-2 bIqExJ Teaser-heading\">Trumps öde i juryns händer</h2></div>","link":"https://www.svd.se/a/W0OBma/trumps-ode-i-juryns-hander","retrieved":1716999022719},{"title":"Två kvinnor häktade misstänkta för grov våldtäkt","contents":"<div class=\"BodyContent-www__sc-uz9q9i-1 hoMPxp\"><h2 class=\"Heading-www__sc-uz9q9i-2 bIqExJ Teaser-heading\">Två kvinnor häktade misstänkta för grov våldtäkt</h2></div>","link":"https://www.svd.se/a/eMKBGO/tva-kvinnor-haktade-for-grov-valdtakt-i-rissne","retrieved":1716999022727},{"title":"”En stor skillnad på Liberalerna och Macron”","contents":"<div class=\"BodyContent-www__sc-uz9q9i-1 hoMPxp\"><h2 class=\"Heading-www__sc-uz9q9i-2 bIqExJ Teaser-heading\">”En stor skillnad på Liberalerna och Macron”</h2></div>","link":"https://www.svd.se/a/yERX9a/liberalernas-karin-karlsbro-vill-inte-samarbeta-med-sd","retrieved":1716999022730},{"title":"Det ryska hybridhotet mot Norden","contents":"Hur ser hybridkrigföringen ut – och vad behöver vi göra för att skydda oss?","link":"https://www.svd.se/a/QMmBoJ/det-ryska-hybridhotet-mot-norden","retrieved":1716999022769,"image":"https://static.svd.se/assets/assets/images/internal-promo/podcast/ledarredaktionen.jpg"},{"title":"Vänta inte – ut med mobilerna från skolan","contents":"<strong>Paulina Neuding: </strong>Vi vet mer än tillräckligt om varför vi behöver ett nationellt mobilförbud.","link":"https://www.svd.se/a/pPAEwE/oecd-visar-varfor-vi-behover-ett-nationellt-mobilforbud","retrieved":1716999022770,"image":"https://svd.vgc.no/v2/images/764d2ba4-30bb-4452-9573-ee94731c15a7?fit=crop&format=jpeg&h=375&q=80&upscale=true&w=666&s=96ff81a782ef55407cc8f9f3dbf5c7c753f74cfd"},{"title":"”Behöver mer än nånsin ge barn perspektiv”","contents":"SvD Junior uppdaterar tidningen – testa en prenumeration.","link":"https://www.svd.se/a/1MBObe/svd-junior-satsar-uppdaterar-tidningen","retrieved":1716566957277},{"title":"Gjorde slut med sitt livs kärlek på grund av exet","contents":"Astrid: Konflikten med bonusbarnets mamma snarare djurisk instinkt än ogillande.","link":"https://www.svd.se/a/pPLeqj/astrids-konflikter-med-bonusbarnets-mamma-slutade-i-separation","retrieved":1716963071720},{"title":"Viaplay: ”Chans till bra avkastning”","contents":"Pressade bolaget tar tillbaka Champions league.","link":"https://www.svd.se/a/dRlQpX/viaplay-tar-tillbaka-uefa-champions-league-chans-till-bra-avkastning","retrieved":1716999022776},{"title":"Ballonger med avföring skickades till Sydkorea","contents":"Därför skickar Nordkorea skräpballonger • Invånare uppmanas stanna inne – ”hotar befolkningen.”","link":"https://www.svd.se/a/dRlQjB/nordkorea-skickar-ballonger-med-skrap-och-avforing-till-sydkorea","retrieved":1716980882985},{"title":"Utredningen mot Alecta försenas","contents":"På grund av FI • Vill undvika spekulationer och rykten.","link":"https://www.svd.se/a/jQBPJe/utredningen-mot-alecta-forsenas-fi-har-inte-presenterat-slutsatser","retrieved":1716999022779},{"title":"Stjärnkrögaren:  Vi måste bli mer självförsörjande","contents":"Pontus Frithiof firar 25 år i branschen – och blickar framåt.","link":"https://www.svd.se/a/Mn3WB0/krogaren-pontus-frithiof-firar-25-ar-i-branschen","retrieved":1716980882991},{"title":"Mästerkockens sommarfestmeny","contents":"Pontus Frithiof bjuder SvD:s läsare på fyra minnesvärda rätter ur karriären.","link":"https://www.svd.se/a/GyaK76/masterkocken-pontus-frithiofs-meny-for-sommarfesten","retrieved":1716980882992},{"title":"IQ-test på fem minuter: Hur intelligent är du?","contents":"Får du 11 rätt har du god chans att komma med i Mensa.","link":"https://www.svd.se/a/GV66l/iq-test-pa-fem-minuter-hur-intelligent-ar-du","retrieved":1716894485297},{"title":"”Hur ska mamma, 93, ge mig sin lägenhet?”","contents":"Advokaten: Du skulle kunna få den idag – under två förutsättningar.","link":"https://www.svd.se/a/AvlxKA/hur-ska-min-93-ariga-mamma-ge-mig-lagenheten-advokaten-svarar","retrieved":1716963071749},{"title":"”Klarar inte av min brors hypokondri”","contents":"”Vad gör jag?” • Psykologen: Inte elakt sätta gränser för sjukdoms­ältande.","link":"https://www.svd.se/a/xm3rxX/vad-gor-jag-at-min-brors-hypokondri-psykologen-svarar-syster","retrieved":1716963071747},{"title":"Hanna Stjärne lämnar SVT","contents":"Suttit som vd sedan 2015 • Här är nya jobbet.","link":"https://www.svd.se/a/xm3zOl/svt-s-vd-lamnar-blir-vd-for-nobelstiftelsen","retrieved":1716973784615},{"title":"”Medierna har utnyttjats – bidrar till polarisering”","contents":"”Kalla faktas” SD-avslöjande väcker frågan: Har nyhetsvärderingen påverkats av trollkonton?","link":"https://www.svd.se/a/5E6e06/hur-paverkas-medier-av-nattroll","retrieved":1716999022810},{"title":"Eva Röse tränar när alla sover: Sömn ytterst trist","contents":"En av landets mest vältränade skådespelare har ett knep när motivationen sviker.","link":"https://www.svd.se/a/nQpdxn/eva-rose-gor-mina-egna-stunts-om-forsakringen-tillater","retrieved":1716790375065},{"title":"Rädda kineser får guldpriset att rusa","contents":"Expert spår att prisfesten fortsätter: ”Ses som ett skydd.”","link":"https://www.svd.se/a/93O8Od/expert-spar-att-guldfesten-fortsatter-nar-radda-kineser-hamstrar","retrieved":1716980882988},{"title":"”Min dotter kommer gå ut gymnasiet utan vänner”","contents":"Lyckan grumlad, skriver ”Ledsen mamma” – läsare reagerar på serien om ensamhet.","link":"https://www.svd.se/a/1MP0pB/ensamhet-kan-vara-en-styrka-lasare-reagerar-pa-idagsidans-serie","retrieved":1716876712430},{"title":"”Jag är starkt bevis på att medicinen fungerar”","contents":"Niklas, 40, enda svensk att testa ny broms­medicin – trotsar läkarnas ”dödsdom”.","link":"https://www.svd.se/a/vgAmOX/ny-bromsmedicin-forlangde-livet-for-als-sjuke-niklas","retrieved":1716790375036},{"title":"”Vi måste kunna välja bort skurkstatsolja”","contents":"Gröna Mobilister: Hög tid för ursprungs­märkning och spårbarhet kring fossil energi.","link":"https://www.svd.se/a/8q6W92/grona-mobilister-vi-maste-kunna-valja-bort-skurkstatsolja","retrieved":1716999022815},{"title":"Slagdängan kapad av högerextremister","contents":"<strong>Tomas Lundin: </strong>”Gucci-nazister” kastar om förutfattade meningar i Tyskland.","link":"https://www.svd.se/a/bmn43d/tyska-elitens-sylt-fest-skapar-debatt-om-hogerextremism","retrieved":1716876712445},{"title":"Professorn: ”Nästan alla kollapser är ofarliga”","contents":"De som får hjärtstopp under långlopp tillhör två grupper • Fyra råd för att undvika kollaps.","link":"https://www.svd.se/a/0VKgKM/professorns-fyra-rad-for-att-undvika-kollaps-under-maratonlopp","retrieved":1716912595067},{"title":"”Kändisbojkotten kan ha fått motsatt effekt”","contents":"Något tycktes ha förändrats – men en månad senare är det tyst om Blockout 2024.","link":"https://www.svd.se/a/Xj8adB/celebrity-blockout-2024-ett-misslyckat-forsok-till-revolution","retrieved":1716876712433},{"title":"Mycket smittsam luftvägsinfektion ökar","contents":"Anledningen: pandemin • SvD svarar på tre frågor om kikhosta.","link":"https://www.svd.se/a/Vzqp8p/svd-svarar-pa-fragor-om-varfor-smittsamma-kikhostan-okar","retrieved":1716963071738},{"title":"Priset på bensin och diesel kan skjuta i höjden","contents":"Stor osäkerhet • Kan avgöras av EU-valet.","link":"https://www.svd.se/a/AvldGq/priset-pa-bensin-och-diesel-kan-skjuta-i-hojden","retrieved":1716876712421},{"title":"Vårt lidande behöver inte vara förutbestämt","contents":"<strong>Johan Eriksson: </strong>Människan är fri och därmed ansvarig – men vi tenderar att fly från denna frihet och detta ansvar.","link":"https://www.svd.se/a/XjgkQ7/recension-heideggerian-existential-therapy-philosophical-ideas-in-practice-av-mo-mandic","retrieved":1716963071827},{"contents":"onsdag 29 maj","link":"https://kund.svd.se/kundinfo/dagens-tidning.html?utm_source=svdse&utm_medium=b2c&utm_content=dt&utm_campaign=dt&intcmp=svdse:b2c:dt:dt","retrieved":1706645476739},{"contents":"<div class=\"MetaWrapper-www__sc-1ploj3h-2 RaKfQ\"><span class=\"MetaText-www__sc-1vxnsg5-0 AccentBoxTeaserLabel-www__sc-1ploj3h-4 kYkGLL idvmnt\">Resa</span><span class=\"MetaText-www__sc-1vxnsg5-0 AccentBoxTeaserPrice-www__sc-1ploj3h-3 kYkGLL gsNijh\">18 950 kr</span></div><h2 class=\"AccentBoxTeaserHeading-www__sc-1ploj3h-1 hYnoFJ\">Bosniens bästa</h2><figure class=\"AccentBoxTeaserImage-www__sc-1ploj3h-5 bNgOTX\"><div class=\"LazyWrapper\" data-controller=\"lazyContent\" data-lazycontent-fire-new-content-event=\"false\" style=\"padding-bottom:56.27%\" data-lazycontentinitialized=\"true\"><noscript><picture class=\"Picture-www__sc-ah7kh1-0 kKnYiz\"><img src=\"https://grafik.svd.se//accent/bdff75183bc939543bfd59b04b7d595468e9aaf09fad561eb67faad8fdd54e5f.jpeg\" alt=\"Bosniens bästa\"/></picture></noscript></div></figure>","link":"https://accent.svd.se/bosniens-basta-med-naturskon-tagresa-och-mostar.html?utm_source=accentbox&utm_medium=svdse&utm_campaign=bosnien","retrieved":1716808095359},{"contents":"<div class=\"MetaWrapper-www__sc-1ploj3h-2 RaKfQ\"><span class=\"MetaText-www__sc-1vxnsg5-0 AccentBoxTeaserLabel-www__sc-1ploj3h-4 kYkGLL idvmnt\">Språkkurser</span><span class=\"MetaText-www__sc-1vxnsg5-0 AccentBoxTeaserPrice-www__sc-1ploj3h-3 kYkGLL gsNijh\">1 mån gratis</span></div><h2 class=\"AccentBoxTeaserHeading-www__sc-1ploj3h-1 hYnoFJ\">Förbättra din spanska</h2><figure class=\"AccentBoxTeaserImage-www__sc-1ploj3h-5 bNgOTX\"><div class=\"LazyWrapper\" data-controller=\"lazyContent\" data-lazycontent-fire-new-content-event=\"false\" style=\"padding-bottom:56.27%\" data-lazycontentinitialized=\"true\"><noscript><picture class=\"Picture-www__sc-ah7kh1-0 kKnYiz\"><img src=\"https://grafik.svd.se//accent/8f8e11c63795851b9c5ced3b695b704e6b80b87876f386bb15fa598a87cff704.jpeg\" alt=\"Förbättra din spanska\"/></picture></noscript></div></figure>","link":"https://www.svd.se/sprakkurser?utm_source=accentbox&utm_medium=svdse&utm_campaign=sprakkurser","retrieved":1716808095368},{"contents":"<div class=\"MetaWrapper-www__sc-1ploj3h-2 RaKfQ\"><span class=\"MetaText-www__sc-1vxnsg5-0 AccentBoxTeaserLabel-www__sc-1ploj3h-4 kYkGLL idvmnt\">Elcykel</span><span class=\"MetaText-www__sc-1vxnsg5-0 AccentBoxTeaserPrice-www__sc-1ploj3h-3 kYkGLL gsNijh\">15 995 kr</span></div><h2 class=\"AccentBoxTeaserHeading-www__sc-1ploj3h-1 hYnoFJ\">Lifebike</h2><figure class=\"AccentBoxTeaserImage-www__sc-1ploj3h-5 bNgOTX\"><div class=\"LazyWrapper\" data-controller=\"lazyContent\" data-lazycontent-fire-new-content-event=\"false\" style=\"padding-bottom:56.27%\" data-lazycontentinitialized=\"true\"><noscript><picture class=\"Picture-www__sc-ah7kh1-0 kKnYiz\"><img src=\"https://grafik.svd.se//accent/af4fcd730a442f6c95f5391d97b073dba3fdc2fb06b257509fc29e64ccc64fe3.jpeg\" alt=\"Lifebike\"/></picture></noscript></div></figure>","link":"https://www.svd.se/butik?utm_source=accentbox&utm_medium=svdse&utm_campaign=elcykel#!/Lifebike-C-MUTE-UNI-G10-8VXL-Bla/p/657619686/category=161312553","retrieved":1716800950237},{"contents":"<div class=\"MetaWrapper-www__sc-1ploj3h-2 RaKfQ\"><span class=\"MetaText-www__sc-1vxnsg5-0 AccentBoxTeaserLabel-www__sc-1ploj3h-4 kYkGLL idvmnt\">Resa</span><span class=\"MetaText-www__sc-1vxnsg5-0 AccentBoxTeaserPrice-www__sc-1ploj3h-3 kYkGLL gsNijh\">42 950 kr</span></div><h2 class=\"AccentBoxTeaserHeading-www__sc-1ploj3h-1 hYnoFJ\">Taiwan – överraskningarnas ö</h2><figure class=\"AccentBoxTeaserImage-www__sc-1ploj3h-5 bNgOTX\"><div class=\"LazyWrapper\" data-controller=\"lazyContent\" data-lazycontent-fire-new-content-event=\"false\" style=\"padding-bottom:56.27%\" data-lazycontentinitialized=\"true\"><noscript><picture class=\"Picture-www__sc-ah7kh1-0 kKnYiz\"><img src=\"https://grafik.svd.se//accent/9c89938663793ab821a0aebdcec12969ca8507a2be7ad98acc425b778fd9815d.jpeg\" alt=\"Taiwan – överraskningarnas ö\"/></picture></noscript></div></figure>","link":"https://accent.svd.se/taiwan-overraskningarnas-o.html?utm_source=accentbox&utm_medium=svdse&utm_campaign=taiwan","retrieved":1716808095369},{"contents":"<div class=\"MetaWrapper-www__sc-1ploj3h-2 RaKfQ\"><span class=\"MetaText-www__sc-1vxnsg5-0 AccentBoxTeaserLabel-www__sc-1ploj3h-4 kYkGLL idvmnt\">Resa</span><span class=\"MetaText-www__sc-1vxnsg5-0 AccentBoxTeaserPrice-www__sc-1ploj3h-3 kYkGLL gsNijh\">74 900 kr</span></div><h2 class=\"AccentBoxTeaserHeading-www__sc-1ploj3h-1 hYnoFJ\">Bergsgorillor och schimpanser i Uganda</h2><figure class=\"AccentBoxTeaserImage-www__sc-1ploj3h-5 bNgOTX\"><div class=\"LazyWrapper\" data-controller=\"lazyContent\" data-lazycontent-fire-new-content-event=\"false\" style=\"padding-bottom:56.27%\" data-lazycontentinitialized=\"true\"><noscript><picture class=\"Picture-www__sc-ah7kh1-0 kKnYiz\"><img src=\"https://grafik.svd.se//accent/a0d2a46f7a79ddc60b24c57e96f212bdff35a644a9e2bb6612ba1cc8502faf0e.jpeg\" alt=\"Bergsgorillor och schimpanser i Uganda\"/></picture></noscript></div></figure>","link":"https://accent.svd.se/bergsgorillor-och-schimpanser-i-uganda-2024.html?utm_source=accentbox&utm_medium=svdse&utm_campaign=uganda","retrieved":1716808095369},{"contents":"<div class=\"MetaWrapper-www__sc-1ploj3h-2 RaKfQ\"><span class=\"MetaText-www__sc-1vxnsg5-0 AccentBoxTeaserLabel-www__sc-1ploj3h-4 kYkGLL idvmnt\">Bok</span><span class=\"MetaText-www__sc-1vxnsg5-0 AccentBoxTeaserPrice-www__sc-1ploj3h-3 kYkGLL gsNijh\">299 kr</span></div><h2 class=\"AccentBoxTeaserHeading-www__sc-1ploj3h-1 hYnoFJ\">Gäddbibeln</h2><figure class=\"AccentBoxTeaserImage-www__sc-1ploj3h-5 bNgOTX\"><div class=\"LazyWrapper\" data-controller=\"lazyContent\" data-lazycontent-fire-new-content-event=\"false\" style=\"padding-bottom:56.27%\" data-lazycontentinitialized=\"true\"><noscript><picture class=\"Picture-www__sc-ah7kh1-0 kKnYiz\"><img src=\"https://grafik.svd.se//accent/347499fd96e50fa660e013bdf0751a449d746e0410f5dbaca74256c88da2ef28.jpeg\" alt=\"Gäddbibeln\"/></picture></noscript></div></figure>","link":"https://www.svd.se/butik?utm_source=accentbox&utm_medium=svdse&utm_campaign=gaddbibeln#!/Gaddbibeln/p/654056760/category=161931057","retrieved":1716800950241}]}